contender/__init__.py
contender/commands.py
contender/utils.py
contender/backends/__init__.py
contender/backends/github.py
contender-0.2.2.dist-info/DESCRIPTION.rst
contender-0.2.2.dist-info/entry_points.txt
contender-0.2.2.dist-info/METADATA
contender-0.2.2.dist-info/metadata.json
contender-0.2.2.dist-info/RECORD
contender-0.2.2.dist-info/top_level.txt
contender-0.2.2.dist-info/WHEEL
