Metadata-Version: 2.0
Name: contender
Version: 0.2.2
Summary: UNKNOWN
Home-page: http://github.com/binarydud/contender
Author: Matt George
Author-email: mgeorge@gmail.com
License: UNKNOWN
Platform: UNKNOWN
Classifier: Development Status :: 3 - Alpha
Classifier: Intended Audience :: Developers
Classifier: Intended Audience :: System Administrators
Classifier: Operating System :: OS Independent
Classifier: Topic :: Software Development
Classifier: Topic :: System
Classifier: Topic :: System :: Software Distribution
Classifier: Programming Language :: Python :: 2.7
Requires-Dist: click
Requires-Dist: github3.py
Requires-Dist: six
